spritze/__init__.py
spritze/__init__.pyi
spritze/exceptions.py
spritze/py.typed
spritze/types.py
spritze/types.pyi
spritze/api/__init__.py
spritze/api/__init__.pyi
spritze/api/core.py
spritze/api/injection.py
spritze/api/provider.py
spritze/core/__init__.py
spritze/core/__init__.pyi
spritze/core/container.py
spritze/core/provider.py
spritze/core/type_map.py
spritze/internal/__init__.py
spritze/internal/globals.py
spritze/internal/type_utils.py
spritze-0.3.9.dist-info/licenses/LICENSE
spritze-0.3.9.dist-info/METADATA
spritze-0.3.9.dist-info/WHEEL
spritze-0.3.9.dist-info/top_level.txt
spritze-0.3.9.dist-info/RECORD
