Metadata-Version: 2.4
Name: spritze
Version: 0.3.9
Summary: A modern, type-safe Dependency Injection framework for Python with support for async/await and context managers.
Author-email: Arseny Seliverstov <asel1x@icloud.com>
License:                                  Apache License
Project-URL: Homepage, https://github.com/aSel1x/spritze
Requires-Python: >=3.12
License-File: LICENSE
Provides-Extra: test
Requires-Dist: pytest; extra == "test"
Requires-Dist: pytest-asyncio; extra == "test"
Provides-Extra: dev
Requires-Dist: ruff; extra == "dev"
Requires-Dist: pip-audit; extra == "dev"
Requires-Dist: basedpyright; extra == "dev"
Provides-Extra: examples
Requires-Dist: uvicorn; extra == "examples"
Requires-Dist: litestar; extra == "examples"
Requires-Dist: flask; extra == "examples"
Requires-Dist: django; extra == "examples"
Dynamic: license-file
